Individual_gate_level/Arbiter.v
`default_nettype none

module Arbiter (
    input wire clk,
    input wire reset,
    
    // 4-port incoming FIFO data streams
    input wire [35:0] rx_data,     
    
    // Port request/valid flags indicating which FIFOs want to transmit
    input wire [3:0] valid_input,  
    
    // Backpressure signal coming downstream from the TX_MAC
    input wire tx_payload_active,  

    // Output to the TX_MAC
    output reg [7:0] tx_data,      
    
    // Output to the TX_MAC to tell it when the frame is officially over
    output wire active_transmit,
    
    // Output to the Port Allocator
    output reg [3:0] rx_grant  
);

    wire [8:0] port_0 = rx_data[8:0];
    wire [8:0] port_1 = rx_data[17:9];
    wire [8:0] port_2 = rx_data[26:18];
    wire [8:0] port_3 = rx_data[35:27];

    reg [1:0] selected_port;
    reg transmitting;
    reg current_eof;

    // --- Combinational EOF Detection ---
    always @(*) begin
        case (selected_port)
            2'b00: current_eof = port_0[8];
            2'b01: current_eof = port_1[8];
            2'b10: current_eof = port_2[8];
            2'b11: current_eof = port_3[8];
            default: current_eof = 1'b0;
        endcase
    end

    // THE HARD-BRAKE: Drop the transmit lock the exact combinational instant EOF appears.
    // This stops the TX_MAC from lingering and freezes the FCS math on the correct hash.
    assign active_transmit = transmitting & ~current_eof;

    // --- SEQUENTIAL LOGIC (State Memory) ---
    always @(posedge clk) begin
        if (reset) begin
            selected_port <= 2'b00;
            transmitting <= 1'b0;
        end 
        else begin
            if (!transmitting) begin
                if (valid_input[0]) begin
                    selected_port <= 2'b00; transmitting <= 1'b1;
                end else if (valid_input[1]) begin
                    selected_port <= 2'b01; transmitting <= 1'b1;
                end else if (valid_input[2]) begin
                    selected_port <= 2'b10; transmitting <= 1'b1;
                end else if (valid_input[3]) begin
                    selected_port <= 2'b11; transmitting <= 1'b1;
                end
            end 
            else begin
                // Drop the internal register on the clock edge following the EOF
                if (current_eof && tx_payload_active) transmitting <= 1'b0;
            end
        end
    end

    // --- COMBINATIONAL LOGIC (Data Routing) ---
    always @(*) begin
        tx_data = 8'h00;
        rx_grant = 4'b0000;
        
        // THE HARD-BRAKE: Sever the read grant instantly to prevent pointer overshoot.
        case (selected_port)
            2'b00: begin 
                tx_data = port_0[7:0]; 
                rx_grant = {3'b000, (transmitting & tx_payload_active & ~current_eof)}; 
            end
            2'b01: begin 
                tx_data = port_1[7:0]; 
                rx_grant = {2'b00, (transmitting & tx_payload_active & ~current_eof), 1'b0}; 
            end
            2'b10: begin 
                tx_data = port_2[7:0]; 
                rx_grant = {1'b0, (transmitting & tx_payload_active & ~current_eof), 2'b00}; 
            end
            2'b11: begin 
                tx_data = port_3[7:0]; 
                rx_grant = {(transmitting & tx_payload_active & ~current_eof), 3'b000}; 
            end
        endcase
    end

endmodule

test_benches/Arbiter_tb.v
`timescale 1ns/1ps

module Arbiter_tb;
    reg clk;
    reg reset;
    reg [35:0] rx_data;
    reg [3:0] valid_input;
    reg tx_payload_active;

    wire [7:0] tx_data;
    wire active_transmit;
    wire [3:0] rx_grant;

    Arbiter uut (
        .clk(clk), .reset(reset),
        .rx_data(rx_data), .valid_input(valid_input), .tx_payload_active(tx_payload_active),
        .tx_data(tx_data), .active_transmit(active_transmit), .rx_grant(rx_grant)
    );

    // 125 MHz Clock
    always #4 clk = ~clk;

    initial begin
        $dumpfile("Arbiter_tb.vcd");
        $dumpvars(0, Arbiter_tb);

        // Initialize signals
        clk = 0; reset = 1;
        rx_data = 36'h0; valid_input = 4'b0000; tx_payload_active = 0;

        #20 reset = 0; #10;

        $display("=== STARTING ARBITER HARD-BRAKE TEST ===");

        // Port 0 Requests Access
        @(negedge clk); 
        valid_input = 4'b0001; 
        rx_data = {27'h0, 1'b0, 8'hAB}; // Standard payload byte (9th bit LOW)
        tx_payload_active = 1; 

        @(negedge clk) rx_data = {27'h0, 1'b0, 8'hCD}; // Standard payload byte
        
        // THE TEST: Trigger EOF (9th bit HIGH)
        // We want to see RX Grant and Active Transmit drop combinationally on this exact cycle.
        @(negedge clk) rx_data = {27'h0, 1'b1, 8'hEF}; // EOF byte

        // The exact next clock cycle, simulate the upstream modules dropping the route
        @(negedge clk) begin
            rx_data = 36'h0;
            valid_input = 4'b0000; 
        end

        // Wait a few cycles to ensure it stays asleep
        #30;

        $display("=== ARBITER TEST COMPLETE ===");
        $finish;
    end

    // Egress Monitor (Now also monitoring the 9th bit directly)
    always @(posedge clk) begin
        $display("[Time %0t] TX Data: %h | RX Grant: %b | Active Transmit Flag: %b | 9th Bit: %b", 
                 $time, tx_data, rx_grant, active_transmit, rx_data[8]);
    end
endmodule

Arbiter_tb.vcd
$date
	Thu Aug 06 14:14:33 2026
$end
$version
	Icarus Verilog
$end
$timescale
	1ps
$end
$scope module Arbiter_tb $end
$var wire 8 ! tx_data [7:0] $end
$var wire 4 " rx_grant [3:0] $end
$var wire 1 # active_transmit $end
$var reg 1 $ clk $end
$var reg 1 % reset $end
$var reg 36 & rx_data [35:0] $end
$var reg 1 ' tx_payload_active $end
$var reg 4 ( valid_input [3:0] $end
$scope module uut $end
$var wire 1 # active_transmit $end
$var wire 1 $ clk $end
$var wire 1 % reset $end
$var wire 36 ) rx_data [35:0] $end
$var wire 1 ' tx_payload_active $end
$var wire 4 * valid_input [3:0] $end
$var wire 9 + port_3 [8:0] $end
$var wire 9 , port_2 [8:0] $end
$var wire 9 - port_1 [8:0] $end
$var wire 9 . port_0 [8:0] $end
$var reg 1 / current_eof $end
$var reg 4 0 rx_grant [3:0] $end
$var reg 2 1 selected_port [1:0] $end
$var reg 1 2 transmitting $end
$var reg 8 3 tx_data [7:0] $end
$upscope $end
$upscope $end
$enddefinitions $end
$comment Show the parameter values. $end
$dumpall
$end
#0
$dumpvars
b0 3
x2
bx 1
b0 0
0/
b0 .
b0 -
b0 ,
b0 +
b0 *
b0 )
b0 (
0'
b0 &
1%
0$
x#
b0 "
b0 !
$end
#4000
0#
02
b0 1
1$
#8000
0$
#12000
1$
#16000
0$
#20000
1$
0%
#24000
0$
#28000
1$
#32000
b10101011 !
b10101011 3
b10101011 .
1'
b10101011 &
b10101011 )
b1 (
b1 *
0$
#36000
b1 "
b1 0
b10101011 !
b10101011 3
1#
12
1$
#40000
b1 "
b1 0
b11001101 !
b11001101 3
b11001101 .
b11001101 &
b11001101 )
0$
#44000
1$
#48000
0#
b0 "
b0 0
b11101111 !
b11101111 3
1/
b111101111 .
b111101111 &
b111101111 )
0$
#52000
b11101111 !
b11101111 3
02
1$
#56000
b0 !
b0 3
0/
b0 .
b0 (
b0 *
b0 &
b0 )
0$
