Individual_gate_level/byte_parser.v
`default_nettype none

module byte_parser (
    input wire clk,
    input wire reset,
    input wire [7:0] rx_data,
    input wire rx_valid,          // Driven by valid_byte_detector
    input wire rx_control_signal, // The GMII rx_dv pin

    output reg [47:0] MAC_destination_address,
    output reg [47:0] MAC_source_address,
    output reg MAC_des_complete,
    output reg MAC_sc_complete,
    output wire [7:0] tx_true_data,
    output wire true_data_valid
);

    reg [3:0] byte_count;

    // Push EVERYTHING that the VBD validates directly into the FIFO
    assign tx_true_data = rx_data;
    assign true_data_valid = rx_valid;

    always @(posedge clk) begin
        // Reset everything when the physical line drops (Inter-Packet Gap)
        if (reset || !rx_control_signal) begin
            byte_count <= 0;
            MAC_des_complete <= 0;
            MAC_sc_complete <= 0;
            MAC_destination_address <= 48'h0;
            MAC_source_address <= 48'h0;
        end 
        else if (rx_valid) begin
            // Prevent integer overflow on long packets
            if (byte_count < 15) begin
                byte_count <= byte_count + 1;
            end

            // The VBD already stripped the Preamble/SFD. 
            // The very first rx_valid byte is the start of the Dest MAC.
            if (byte_count < 6) begin
                MAC_destination_address <= {MAC_destination_address[39:0], rx_data};
                if (byte_count == 5) MAC_des_complete <= 1; // Wake up the CAM
            end
            
            // Parse the Source MAC
            else if (byte_count < 12) begin
                MAC_source_address <= {MAC_source_address[39:0], rx_data};
                if (byte_count == 11) MAC_sc_complete <= 1; // Wake up the Learning Engine
            end
        end
    end
endmodule

test_benches/byte_parser_tb.v
`timescale 1ns/1ps

module byte_parser_tb;
    reg clk;
    reg reset;
    reg [7:0] rx_data;
    reg rx_valid;
    reg rx_control_signal;

    wire [47:0] MAC_destination_address;
    wire [47:0] MAC_source_address;
    wire MAC_des_complete;
    wire MAC_sc_complete;
    wire [7:0] tx_true_data;
    wire true_data_valid;

    byte_parser uut (
        .clk(clk), .reset(reset),
        .rx_data(rx_data), .rx_valid(rx_valid), .rx_control_signal(rx_control_signal),
        .MAC_destination_address(MAC_destination_address),
        .MAC_source_address(MAC_source_address),
        .MAC_des_complete(MAC_des_complete),
        .MAC_sc_complete(MAC_sc_complete),
        .tx_true_data(tx_true_data),
        .true_data_valid(true_data_valid)
    );

    always #4 clk = ~clk;

    integer i;

    initial begin
        $dumpfile("byte_parser_tb.vcd");
        $dumpvars(0, byte_parser_tb);

        clk = 0; reset = 1;
        rx_data = 8'h00; rx_valid = 0; rx_control_signal = 0;

        #20 reset = 0; #10;

        $display("=== STARTING PARSER VBD-TRUST TEST ===");
        
        // Link goes active, but VBD hasn't validated data yet
        @(negedge clk) rx_control_signal = 1; 

        // Simulating the time the VBD spends eating the Preamble and SFD
        for (i=0; i<8; i=i+1) begin
            rx_data = 8'h00; rx_valid = 0; @(negedge clk);
        end

        // The VBD sees the first byte of the Dest MAC and asserts rx_valid!
        rx_valid = 1;

        // Dest MAC (00:11:22:33:44:55)
        rx_data = 8'h00; @(negedge clk);
        rx_data = 8'h11; @(negedge clk);
        rx_data = 8'h22; @(negedge clk);
        rx_data = 8'h33; @(negedge clk);
        rx_data = 8'h44; @(negedge clk);
        rx_data = 8'h55; @(negedge clk);

        // Source MAC (AA:BB:CC:DD:EE:FF)
        rx_data = 8'hAA; @(negedge clk);
        rx_data = 8'hBB; @(negedge clk);
        rx_data = 8'hCC; @(negedge clk);
        rx_data = 8'hDD; @(negedge clk);
        rx_data = 8'hEE; @(negedge clk);
        rx_data = 8'hFF; @(negedge clk);
        
        // A few payload bytes
        rx_data = 8'h08; @(negedge clk);
        rx_data = 8'h00; @(negedge clk);
        rx_data = 8'h10; @(negedge clk);
        rx_data = 8'h11; @(negedge clk);

        // End of packet
        rx_control_signal = 0; rx_valid = 0; rx_data = 8'h00;
        
        #20 $display("=== PARSER TEST COMPLETE ===");
        $finish;
    end

    always @(posedge clk) begin
        if (rx_control_signal)
            $display("[Time %0t] VBD Output: %h (Valid: %b) | Parser Passing: %h (Valid: %b) | Dest Complete: %b", 
                     $time, rx_data, rx_valid, tx_true_data, true_data_valid, MAC_des_complete);
    end
endmodule

byte_parser_tb.vcd
$date
	Thu Aug 06 14:09:37 2026
$end
$version
	Icarus Verilog
$end
$timescale
	1ps
$end
$scope module byte_parser_tb $end
$var wire 8 ! tx_true_data [7:0] $end
$var wire 1 " true_data_valid $end
$var wire 48 # MAC_source_address [47:0] $end
$var wire 1 $ MAC_sc_complete $end
$var wire 48 % MAC_destination_address [47:0] $end
$var wire 1 & MAC_des_complete $end
$var reg 1 ' clk $end
$var reg 1 ( reset $end
$var reg 1 ) rx_control_signal $end
$var reg 8 * rx_data [7:0] $end
$var reg 1 + rx_valid $end
$var integer 32 , i [31:0] $end
$scope module uut $end
$var wire 1 ' clk $end
$var wire 1 ( reset $end
$var wire 1 ) rx_control_signal $end
$var wire 8 - rx_data [7:0] $end
$var wire 1 + rx_valid $end
$var wire 1 " true_data_valid $end
$var wire 8 . tx_true_data [7:0] $end
$var reg 1 & MAC_des_complete $end
$var reg 48 / MAC_destination_address [47:0] $end
$var reg 1 $ MAC_sc_complete $end
$var reg 48 0 MAC_source_address [47:0] $end
$var reg 4 1 byte_count [3:0] $end
$upscope $end
$upscope $end
$enddefinitions $end
$comment Show the parameter values. $end
$dumpall
$end
#0
$dumpvars
bx 1
bx 0
bx /
b0 .
b0 -
bx ,
0+
b0 *
0)
1(
0'
x&
bx %
x$
bx #
0"
b0 !
$end
#4000
b0 #
b0 0
b0 %
b0 /
0$
0&
b0 1
1'
#8000
0'
#12000
1'
#16000
0'
#20000
1'
0(
#24000
0'
#28000
1'
#32000
b0 ,
1)
0'
#36000
1'
#40000
b1 ,
0'
#44000
1'
#48000
b10 ,
0'
#52000
1'
#56000
b11 ,
0'
#60000
1'
#64000
b100 ,
0'
#68000
1'
#72000
b101 ,
0'
#76000
1'
#80000
b110 ,
0'
#84000
1'
#88000
b111 ,
0'
#92000
1'
#96000
1"
1+
b1000 ,
0'
#100000
b1 1
1'
#104000
b10001 !
b10001 .
b10001 *
b10001 -
0'
#108000
b10001 %
b10001 /
b10 1
1'
#112000
b100010 !
b100010 .
b100010 *
b100010 -
0'
#116000
b1000100100010 %
b1000100100010 /
b11 1
1'
#120000
b110011 !
b110011 .
b110011 *
b110011 -
0'
#124000
b100010010001000110011 %
b100010010001000110011 /
b100 1
1'
#128000
b1000100 !
b1000100 .
b1000100 *
b1000100 -
0'
#132000
b10001001000100011001101000100 %
b10001001000100011001101000100 /
b101 1
1'
#136000
b1010101 !
b1010101 .
b1010101 *
b1010101 -
0'
#140000
1&
b1000100100010001100110100010001010101 %
b1000100100010001100110100010001010101 /
b110 1
1'
#144000
b10101010 !
b10101010 .
b10101010 *
b10101010 -
0'
#148000
b10101010 #
b10101010 0
b111 1
1'
#152000
b10111011 !
b10111011 .
b10111011 *
b10111011 -
0'
#156000
b1010101010111011 #
b1010101010111011 0
b1000 1
1'
#160000
b11001100 !
b11001100 .
b11001100 *
b11001100 -
0'
#164000
b101010101011101111001100 #
b101010101011101111001100 0
b1001 1
1'
#168000
b11011101 !
b11011101 .
b11011101 *
b11011101 -
0'
#172000
b10101010101110111100110011011101 #
b10101010101110111100110011011101 0
b1010 1
1'
#176000
b11101110 !
b11101110 .
b11101110 *
b11101110 -
0'
#180000
b1010101010111011110011001101110111101110 #
b1010101010111011110011001101110111101110 0
b1011 1
1'
#184000
b11111111 !
b11111111 .
b11111111 *
b11111111 -
0'
#188000
1$
b101010101011101111001100110111011110111011111111 #
b101010101011101111001100110111011110111011111111 0
b1100 1
1'
#192000
b1000 !
b1000 .
b1000 *
b1000 -
0'
#196000
b1101 1
1'
#200000
b0 !
b0 .
b0 *
b0 -
0'
#204000
b1110 1
1'
#208000
b10000 !
b10000 .
b10000 *
b10000 -
0'
#212000
b1111 1
1'
#216000
b10001 !
b10001 .
b10001 *
b10001 -
0'
#220000
1'
#224000
b0 !
b0 .
b0 *
b0 -
0"
0+
0)
0'
#228000
b0 #
b0 0
b0 %
b0 /
0$
0&
b0 1
1'
