Individual_gate_level/CAM_write_arbiter.v
`default_nettype none

module CAM_Write_Arbiter(
    input wire clk, 
    input wire reset,
    
    // --- Inputs from RX Port 0 Learning Engine ---
    input wire we_0,
    input wire [47:0] mac_0,
    input wire [3:0] port_0,
    
    // --- Inputs from RX Port 1 Learning Engine ---
    input wire we_1,
    input wire [47:0] mac_1,
    input wire [3:0] port_1,
    
    // --- Inputs from RX Port 2 Learning Engine ---
    input wire we_2,
    input wire [47:0] mac_2,
    input wire [3:0] port_2,
    
    // --- Inputs from RX Port 3 Learning Engine ---
    input wire we_3,
    input wire [47:0] mac_3,
    input wire [3:0] port_3,
    
    // --- Unified Outputs to the Central CAM ---
    output reg cam_we,
    output reg [47:0] cam_write_mac,
    output reg [3:0] cam_write_port
);

    // Buffers to latch incoming 1-cycle pulses so they aren't lost
    reg req_pending [0:3];
    reg [47:0] latched_mac [0:3];
    reg [3:0] latched_port [0:3];

    integer i;

    always @(posedge clk) begin
        if (reset) begin
            cam_we <= 1'b0;
            cam_write_mac <= 48'h0;
            cam_write_port <= 4'h0;
            
            for (i = 0; i < 4; i = i + 1) begin
                req_pending[i] <= 1'b0;
                latched_mac[i] <= 48'h0;
                latched_port[i] <= 4'h0;
            end
        end else begin
            
            // ---------------------------------------------------------
            // 1. THE LATCH STAGE
            // If any learning engine pulses 'we' for a clock cycle, 
            // instantly save its data and raise its pending flag.
            // ---------------------------------------------------------
            if (we_0) begin 
                req_pending[0] <= 1'b1; latched_mac[0] <= mac_0; latched_port[0] <= port_0; 
            end
            if (we_1) begin 
                req_pending[1] <= 1'b1; latched_mac[1] <= mac_1; latched_port[1] <= port_1; 
            end
            if (we_2) begin 
                req_pending[2] <= 1'b1; latched_mac[2] <= mac_2; latched_port[2] <= port_2; 
            end
            if (we_3) begin 
                req_pending[3] <= 1'b1; latched_mac[3] <= mac_3; latched_port[3] <= port_3; 
            end

            // ---------------------------------------------------------
            // 2. THE SERVICE STAGE (Fixed Priority Encoder)
            // Look at the pending flags. Service the lowest port number
            // first. Once serviced, clear its flag so the next port 
            // can be serviced on the next clock cycle.
            // ---------------------------------------------------------
            if (req_pending[0]) begin
                cam_we <= 1'b1;
                cam_write_mac <= latched_mac[0];
                cam_write_port <= latched_port[0];
                req_pending[0] <= 1'b0; // Clear the flag so it doesn't write twice
            end
            else if (req_pending[1]) begin
                cam_we <= 1'b1;
                cam_write_mac <= latched_mac[1];
                cam_write_port <= latched_port[1];
                req_pending[1] <= 1'b0; 
            end
            else if (req_pending[2]) begin
                cam_we <= 1'b1;
                cam_write_mac <= latched_mac[2];
                cam_write_port <= latched_port[2];
                req_pending[2] <= 1'b0; 
            end
            else if (req_pending[3]) begin
                cam_we <= 1'b1;
                cam_write_mac <= latched_mac[3];
                cam_write_port <= latched_port[3];
                req_pending[3] <= 1'b0; 
            end
            else begin
                // If nobody is pending, drop the write enable to protect the memory
                cam_we <= 1'b0;
            end

        end
    end

endmodule

test_benches/CAM_write_arbiter_tb.v
`timescale 1ns/1ps

module CAM_Write_Arbiter_tb;
    reg clk, reset;
    
    reg we_0, we_1, we_2, we_3;
    reg [47:0] mac_0, mac_1, mac_2, mac_3;
    reg [3:0] port_0, port_1, port_2, port_3;
    
    wire cam_we;
    wire [47:0] cam_write_mac;
    wire [3:0] cam_write_port;

    CAM_Write_Arbiter u1(
        .clk(clk), .reset(reset),
        .we_0(we_0), .mac_0(mac_0), .port_0(port_0),
        .we_1(we_1), .mac_1(mac_1), .port_1(port_1),
        .we_2(we_2), .mac_2(mac_2), .port_2(port_2),
        .we_3(we_3), .mac_3(mac_3), .port_3(port_3),
        .cam_we(cam_we), .cam_write_mac(cam_write_mac), .cam_write_port(cam_write_port)
    );

    always #5 clk = ~clk;

    initial begin
        $dumpfile("CAM_Write_Arbiter_tb.vcd");
        $dumpvars(0, CAM_Write_Arbiter_tb);

        clk = 0; reset = 1;
        we_0 = 0; we_1 = 0; we_2 = 0; we_3 = 0;
        mac_0 = 48'hA; mac_1 = 48'hB; mac_2 = 48'hC; mac_3 = 48'hD;
        port_0 = 4'd0; port_1 = 4'd1; port_2 = 4'd2; port_3 = 4'd3;

        #10;
        reset = 0;
        #10;

        // Port 1 and Port 2 fire in the exact same cycle
        @(negedge clk) begin
            we_1 = 1;
            we_2 = 1;
        end
        
        // Cycle 1: The Arbiter latches the requests internally. Output is still 0.
        @(negedge clk) begin
            we_1 = 0;
            we_2 = 0;
            $display("Arbitration Cycle 1 (Latch Stage)   : Writing MAC %h to port %d (we: %b)", cam_write_mac, cam_write_port, cam_we);
        end
        
        // Cycle 2: The Arbiter services Port 1.
        @(negedge clk) begin
            $display("Arbitration Cycle 2 (Service Port 1): Writing MAC %h to port %d (we: %b)", cam_write_mac, cam_write_port, cam_we);
        end
        
        // Cycle 3: The Arbiter services Port 2 from its internal buffer.
        @(negedge clk) begin
            $display("Arbitration Cycle 3 (Service Port 2): Writing MAC %h to port %d (we: %b)", cam_write_mac, cam_write_port, cam_we);
        end
        
        // Cycle 4: Both flags are cleared. The Arbiter drops 'we' to protect memory.
        @(negedge clk) begin
            $display("Arbitration Cycle 4 (Idle/Clear)    : we: %b (Expected 0)", cam_we);
        end

        $finish;
    end
endmodule

CAM_Write_Arbiter_tb.vcd
$date
	Wed Aug 05 15:34:59 2026
$end
$version
	Icarus Verilog
$end
$timescale
	1ps
$end
$scope module CAM_Write_Arbiter_tb $end
$var wire 4 ! cam_write_port [3:0] $end
$var wire 48 " cam_write_mac [47:0] $end
$var wire 1 # cam_we $end
$var reg 1 $ clk $end
$var reg 48 % mac_0 [47:0] $end
$var reg 48 & mac_1 [47:0] $end
$var reg 48 ' mac_2 [47:0] $end
$var reg 48 ( mac_3 [47:0] $end
$var reg 4 ) port_0 [3:0] $end
$var reg 4 * port_1 [3:0] $end
$var reg 4 + port_2 [3:0] $end
$var reg 4 , port_3 [3:0] $end
$var reg 1 - reset $end
$var reg 1 . we_0 $end
$var reg 1 / we_1 $end
$var reg 1 0 we_2 $end
$var reg 1 1 we_3 $end
$scope module u1 $end
$var wire 1 $ clk $end
$var wire 48 2 mac_0 [47:0] $end
$var wire 48 3 mac_1 [47:0] $end
$var wire 48 4 mac_2 [47:0] $end
$var wire 48 5 mac_3 [47:0] $end
$var wire 4 6 port_0 [3:0] $end
$var wire 4 7 port_1 [3:0] $end
$var wire 4 8 port_2 [3:0] $end
$var wire 4 9 port_3 [3:0] $end
$var wire 1 - reset $end
$var wire 1 . we_0 $end
$var wire 1 / we_1 $end
$var wire 1 0 we_2 $end
$var wire 1 1 we_3 $end
$var reg 1 # cam_we $end
$var reg 48 : cam_write_mac [47:0] $end
$var reg 4 ; cam_write_port [3:0] $end
$var integer 32 < i [31:0] $end
$upscope $end
$upscope $end
$enddefinitions $end
$comment Show the parameter values. $end
$dumpall
$end
#0
$dumpvars
bx <
bx ;
bx :
b11 9
b10 8
b1 7
b0 6
b1101 5
b1100 4
b1011 3
b1010 2
01
00
0/
0.
1-
b11 ,
b10 +
b1 *
b0 )
b1101 (
b1100 '
b1011 &
b1010 %
0$
x#
bx "
bx !
$end
#5000
b0 !
b0 ;
b0 "
b0 :
0#
b100 <
1$
#10000
0$
0-
#15000
1$
#20000
10
1/
0$
#25000
1$
#30000
00
0/
0$
#35000
b1 !
b1 ;
b1011 "
b1011 :
1#
1$
#40000
0$
#45000
b10 !
b10 ;
b1100 "
b1100 :
1$
#50000
0$
#55000
0#
1$
