Individual_gate_level/FCS.v
module FCS(  // auto generated by bues.ch, since we look into the future to limit clock cycles (not shifting 8 times)
    input [7:0] data, // rx_data
    input clk, reset, valid_data, // tells us if we are ok to keep going or FIFO paused
    input done, // 9th bit of FIFO is 1
    input poison,
    output [31:0] rx_crc
);
    wire [31:0] crcOut;
    reg [31:0] crcIn;

   assign rx_crc = poison ? crcOut : ~crcOut;; //does not give the  correct output if poison

    assign crcOut[0] = crcIn[2] ^ crcIn[8] ^ data[2];
    assign crcOut[1] = crcIn[0] ^ crcIn[3] ^ crcIn[9] ^ data[0] ^ data[3];
    assign crcOut[2] = crcIn[0] ^ crcIn[1] ^ crcIn[4] ^ crcIn[10] ^ data[0] ^ data[1] ^ data[4];
    assign crcOut[3] = crcIn[1] ^ crcIn[2] ^ crcIn[5] ^ crcIn[11] ^ data[1] ^ data[2] ^ data[5];
    assign crcOut[4] = crcIn[0] ^ crcIn[2] ^ crcIn[3] ^ crcIn[6] ^ crcIn[12] ^ data[0] ^ data[2] ^ data[3] ^ data[6];
    assign crcOut[5] = crcIn[1] ^ crcIn[3] ^ crcIn[4] ^ crcIn[7] ^ crcIn[13] ^ data[1] ^ data[3] ^ data[4] ^ data[7];
    assign crcOut[6] = crcIn[4] ^ crcIn[5] ^ crcIn[14] ^ data[4] ^ data[5];
    assign crcOut[7] = crcIn[0] ^ crcIn[5] ^ crcIn[6] ^ crcIn[15] ^ data[0] ^ data[5] ^ data[6];
    assign crcOut[8] = crcIn[1] ^ crcIn[6] ^ crcIn[7] ^ crcIn[16] ^ data[1] ^ data[6] ^ data[7];
    assign crcOut[9] = crcIn[7] ^ crcIn[17] ^ data[7];
    assign crcOut[10] = crcIn[2] ^ crcIn[18] ^ data[2];
    assign crcOut[11] = crcIn[3] ^ crcIn[19] ^ data[3];
    assign crcOut[12] = crcIn[0] ^ crcIn[4] ^ crcIn[20] ^ data[0] ^ data[4];
    assign crcOut[13] = crcIn[0] ^ crcIn[1] ^ crcIn[5] ^ crcIn[21] ^ data[0] ^ data[1] ^ data[5];
    assign crcOut[14] = crcIn[1] ^ crcIn[2] ^ crcIn[6] ^ crcIn[22] ^ data[1] ^ data[2] ^ data[6];
    assign crcOut[15] = crcIn[2] ^ crcIn[3] ^ crcIn[7] ^ crcIn[23] ^ data[2] ^ data[3] ^ data[7];
    assign crcOut[16] = crcIn[0] ^ crcIn[2] ^ crcIn[3] ^ crcIn[4] ^ crcIn[24] ^ data[0] ^ data[2] ^ data[3] ^ data[4];
    assign crcOut[17] = crcIn[0] ^ crcIn[1] ^ crcIn[3] ^ crcIn[4] ^ crcIn[5] ^ crcIn[25] ^ data[0] ^ data[1] ^ data[3] ^ data[4] ^ data[5];
    assign crcOut[18] = crcIn[0] ^ crcIn[1] ^ crcIn[2] ^ crcIn[4] ^ crcIn[5] ^ crcIn[6] ^ crcIn[26] ^ data[0] ^ data[1] ^ data[2] ^ data[4] ^ data[5] ^ data[6];
    assign crcOut[19] = crcIn[1] ^ crcIn[2] ^ crcIn[3] ^ crcIn[5] ^ crcIn[6] ^ crcIn[7] ^ crcIn[27] ^ data[1] ^ data[2] ^ data[3] ^ data[5] ^ data[6] ^ data[7];
    assign crcOut[20] = crcIn[3] ^ crcIn[4] ^ crcIn[6] ^ crcIn[7] ^ crcIn[28] ^ data[3] ^ data[4] ^ data[6] ^ data[7];
    assign crcOut[21] = crcIn[2] ^ crcIn[4] ^ crcIn[5] ^ crcIn[7] ^ crcIn[29] ^ data[2] ^ data[4] ^ data[5] ^ data[7];
    assign crcOut[22] = crcIn[2] ^ crcIn[3] ^ crcIn[5] ^ crcIn[6] ^ crcIn[30] ^ data[2] ^ data[3] ^ data[5] ^ data[6];
    assign crcOut[23] = crcIn[3] ^ crcIn[4] ^ crcIn[6] ^ crcIn[7] ^ crcIn[31] ^ data[3] ^ data[4] ^ data[6] ^ data[7];
    assign crcOut[24] = crcIn[0] ^ crcIn[2] ^ crcIn[4] ^ crcIn[5] ^ crcIn[7] ^ data[0] ^ data[2] ^ data[4] ^ data[5] ^ data[7];
    assign crcOut[25] = crcIn[0] ^ crcIn[1] ^ crcIn[2] ^ crcIn[3] ^ crcIn[5] ^ crcIn[6] ^ data[0] ^ data[1] ^ data[2] ^ data[3] ^ data[5] ^ data[6];
    assign crcOut[26] = crcIn[0] ^ crcIn[1] ^ crcIn[2] ^ crcIn[3] ^ crcIn[4] ^ crcIn[6] ^ crcIn[7] ^ data[0] ^ data[1] ^ data[2] ^ data[3] ^ data[4] ^ data[6] ^ data[7];
    assign crcOut[27] = crcIn[1] ^ crcIn[3] ^ crcIn[4] ^ crcIn[5] ^ crcIn[7] ^ data[1] ^ data[3] ^ data[4] ^ data[5] ^ data[7];
    assign crcOut[28] = crcIn[0] ^ crcIn[4] ^ crcIn[5] ^ crcIn[6] ^ data[0] ^ data[4] ^ data[5] ^ data[6];
    assign crcOut[29] = crcIn[0] ^ crcIn[1] ^ crcIn[5] ^ crcIn[6] ^ crcIn[7] ^ data[0] ^ data[1] ^ data[5] ^ data[6] ^ data[7];
    assign crcOut[30] = crcIn[0] ^ crcIn[1] ^ crcIn[6] ^ crcIn[7] ^ data[0] ^ data[1] ^ data[6] ^ data[7];
    assign crcOut[31] = crcIn[1] ^ crcIn[7] ^ data[1] ^ data[7];

    always @(posedge clk) begin
        if (reset) begin
            crcIn <= 32'hFF_FF_FF_FF;
        end
        else if (!valid_data || done) begin
            crcIn <= crcIn;
        end
        else begin
            crcIn <= crcOut; // crcIn is the old crcOut
        end
    end

endmodule

test_benches/FCS_tb.v
`timescale 1ns/1ps

module FCS_tb;

    reg [7:0] data;
    reg clk, reset, valid_data; 
    reg done; 
    reg poison; 
    wire [31:0] rx_crc;

    reg display;

    FCS u1(
        .data(data),
        .clk(clk),
        .reset(reset),
        .valid_data(valid_data),
        .done(done),
        .poison(poison), 
        .rx_crc(rx_crc)
    );

    always #4 clk = ~clk;

    integer i;
    reg [31:0] expected_out; 
    reg [31:0] magic_res_FCS;
    wire match;

    assign match = expected_out == rx_crc;
    
    initial begin
        $dumpfile("FCS_tb.vcd");
        $dumpvars(0, FCS_tb);

        clk = 0;
        reset = 0;
        valid_data = 1;
        done = 0;
        display = 0;
        poison = 0; // Default to clean packet

        // empty data (data = h'00):
        data = 8'h00;
        repeat (2) begin
            @(negedge clk) begin
                reset = ~reset; 
                #1;
            end
        end
        $display("data is h'00 and will run for 4 clock cycles:");
        expected_out = 32'h2144DF1C;
        repeat (2) begin 
            @(negedge clk) begin
            end
        end

        @(negedge clk);
        repeat (2) begin
            display = ~display; 
            #1;
        end
        $display("The expected output is: %h", expected_out);
        $display("The actual output is: %h", rx_crc);
        $display("Are they the same? (1 is yes 0 is no): %b", match);

        // standard ASCII test (123456789)
        $display("data is for the ASCII test (123456789) and will run for 9 clock cycles:");
        data = 32'h31;
        reset = 1;
        @(negedge clk) begin
            reset = 0;
        end

        expected_out = 32'hCBF43926;
        repeat (8) begin 
            @(negedge clk) begin
                data = data + 1;
            end
        end
        
        // FREEZE THE ENGINE HERE:
        // Pull valid_data low instantly before the delays let the clock tick forward
        valid_data = 0; 
        
        #1;
        repeat (2) begin
            display = ~display; 
            #1;
        end
        $display("The expected output is: %h", expected_out);
        $display("The actual output is: %h", rx_crc);
        $display("Are they the same? (1 is yes 0 is no): %b", match);
        
        // POISON TEST
        $display("Testing poison flag injection:");
        @(negedge clk) begin
            poison = 1;
            expected_out = ~32'hCBF43926; // Expect the raw (un-inverted) crcOut
        end
        #1;
        $display("The expected output is: %h", expected_out);
        $display("The actual output is: %h", rx_crc);
        $display("Are they the same? (1 is yes 0 is no): %b", match);

        $finish;
    end
endmodule

FCS_tb.vcd
$date
	Wed Aug 05 15:46:44 2026
$end
$version
	Icarus Verilog
$end
$timescale
	1ps
$end
$scope module FCS_tb $end
$var wire 32 ! rx_crc [31:0] $end
$var wire 1 " match $end
$var reg 1 # clk $end
$var reg 8 $ data [7:0] $end
$var reg 1 % display $end
$var reg 1 & done $end
$var reg 32 ' expected_out [31:0] $end
$var reg 1 ( poison $end
$var reg 1 ) reset $end
$var reg 1 * valid_data $end
$scope module u1 $end
$var wire 1 # clk $end
$var wire 8 + data [7:0] $end
$var wire 1 & done $end
$var wire 1 ( poison $end
$var wire 1 ) reset $end
$var wire 1 * valid_data $end
$var wire 32 , rx_crc [31:0] $end
$var wire 32 - crcOut [31:0] $end
$var reg 32 . crcIn [31:0] $end
$upscope $end
$upscope $end
$enddefinitions $end
$comment Show the parameter values. $end
$dumpall
$end
#0
$dumpvars
bx .
bx -
bx ,
b0 +
1*
0)
0(
bx '
0&
0%
b0 $
0#
x"
bx !
$end
#4000
1#
#8000
1)
0#
#12000
b11010010000000101110111110001101 !
b11010010000000101110111110001101 ,
b101101111111010001000001110010 -
b11111111111111111111111111111111 .
1#
#16000
0)
0#
#17000
0"
b100001010001001101111100011100 '
#20000
b1000001110110010001001011111111 !
b1000001110110010001001011111111 ,
b10111110001001101110110100000000 -
b101101111111010001000001110010 .
1#
#24000
0#
#28000
b11111111010000011101100100010010 !
b11111111010000011101100100010010 ,
b101111100010011011101101 -
b10111110001001101110110100000000 .
1#
#32000
0#
#36000
1"
b100001010001001101111100011100 !
b100001010001001101111100011100 ,
b11011110101110110010000011100011 -
b101111100010011011101101 .
1#
#40000
1%
0#
#41000
0%
#42000
0"
b1110000100110101101111100100110 !
b1110000100110101101111100100110 ,
b10001111011001010010000011011001 -
1)
b110001 $
b110001 +
#44000
b10000011110111001110111110110111 !
b10000011110111001110111110110111 ,
b1111100001000110001000001001000 -
b11111111111111111111111111111111 .
1#
#48000
b11001011111101000011100100100110 '
0)
0#
#52000
b11010110010110100001010101110111 !
b11010110010110100001010101110111 ,
b101001101001011110101010001000 -
b1111100001000110001000001001000 .
1#
#56000
b1001111010100110100010011001101 !
b1001111010100110100010011001101 ,
b10110000101011001011101100110010 -
b110010 $
b110010 +
0#
#60000
b11111111010011110101001101000100 !
b11111111010011110101001101000100 ,
b101100001010110010111011 -
b10110000101011001011101100110010 .
1#
#64000
b10001000010010000110001111010010 !
b10001000010010000110001111010010 ,
b1110111101101111001110000101101 -
b110011 $
b110011 +
0#
#68000
b101100001110111010100000000 !
b101100001110111010100000000 ,
b11111010011110001000101011111111 -
b1110111101101111001110000101101 .
1#
#72000
b10011011111000111110000010100011 !
b10011011111000111110000010100011 ,
b1100100000111000001111101011100 -
b110100 $
b110100 +
0#
#76000
b10111100111100100000101010001010 !
b10111100111100100000101010001010 ,
b1000011000011011111010101110101 -
b1100100000111000001111101011100 .
1#
#80000
b11001011111101010011101000011100 !
b11001011111101010011101000011100 ,
b110100000010101100010111100011 -
b110101 $
b110101 +
0#
#84000
b10010000011110111000001011011011 !
b10010000011110111000001011011011 ,
b1101111100001000111110100100100 -
b110100000010101100010111100011 .
1#
#88000
b1001011100101101001101100001 !
b1001011100101101001101100001 ,
b11110110100011010010110010011110 -
b110110 $
b110110 +
0#
#92000
b100111000001000101100100001001 !
b100111000001000101100100001001 ,
b11011000111110111010011011110110 -
b11110110100011010010110010011110 .
1#
#96000
b1010000000000110110100110011111 !
b1010000000000110110100110011111 ,
b10101111111111001001011001100000 -
b110111 $
b110111 +
0#
#100000
b1010010111111100011100111110 !
b1010010111111100011100111110 ,
b11110101101000000011100011000001 -
b10101111111111001001011001100000 .
1#
#104000
b10011010111000001101101010101111 !
b10011010111000001101101010101111 ,
b1100101000111110010010101010000 -
b111000 $
b111000 +
0#
#108000
b10111100111100110000100110110000 !
b10111100111100110000100110110000 ,
b1000011000011001111011001001111 -
b1100101000111110010010101010000 .
1#
#112000
1"
b11001011111101000011100100100110 !
b11001011111101000011100100100110 ,
b110100000010111100011011011001 -
0*
b111001 $
b111001 +
0#
#113000
1%
#114000
0%
#116000
1#
#120000
b110100000010111100011011011001 !
b110100000010111100011011011001 ,
1"
b110100000010111100011011011001 '
1(
0#
