Individual_gate_level/FCS.v
module FCS(  // auto generated by bues.ch, since we look into the future to limit clock cycles (not shifting 8 times)
    input [7:0] data, // rx_data
    input clk, reset, valid_data, // tells us if we are ok to keep going or FIFO paused
    input done, // 9th bit of FIFO is 1
    output [31:0] rx_crc
);
    wire [31:0] crcOut;
    reg [31:0] crcIn;

    assign rx_crc = ~crcOut; //output inversion

    assign crcOut[0] = crcIn[2] ^ crcIn[8] ^ data[2];
    assign crcOut[1] = crcIn[0] ^ crcIn[3] ^ crcIn[9] ^ data[0] ^ data[3];
    assign crcOut[2] = crcIn[0] ^ crcIn[1] ^ crcIn[4] ^ crcIn[10] ^ data[0] ^ data[1] ^ data[4];
    assign crcOut[3] = crcIn[1] ^ crcIn[2] ^ crcIn[5] ^ crcIn[11] ^ data[1] ^ data[2] ^ data[5];
    assign crcOut[4] = crcIn[0] ^ crcIn[2] ^ crcIn[3] ^ crcIn[6] ^ crcIn[12] ^ data[0] ^ data[2] ^ data[3] ^ data[6];
    assign crcOut[5] = crcIn[1] ^ crcIn[3] ^ crcIn[4] ^ crcIn[7] ^ crcIn[13] ^ data[1] ^ data[3] ^ data[4] ^ data[7];
    assign crcOut[6] = crcIn[4] ^ crcIn[5] ^ crcIn[14] ^ data[4] ^ data[5];
    assign crcOut[7] = crcIn[0] ^ crcIn[5] ^ crcIn[6] ^ crcIn[15] ^ data[0] ^ data[5] ^ data[6];
    assign crcOut[8] = crcIn[1] ^ crcIn[6] ^ crcIn[7] ^ crcIn[16] ^ data[1] ^ data[6] ^ data[7];
    assign crcOut[9] = crcIn[7] ^ crcIn[17] ^ data[7];
    assign crcOut[10] = crcIn[2] ^ crcIn[18] ^ data[2];
    assign crcOut[11] = crcIn[3] ^ crcIn[19] ^ data[3];
    assign crcOut[12] = crcIn[0] ^ crcIn[4] ^ crcIn[20] ^ data[0] ^ data[4];
    assign crcOut[13] = crcIn[0] ^ crcIn[1] ^ crcIn[5] ^ crcIn[21] ^ data[0] ^ data[1] ^ data[5];
    assign crcOut[14] = crcIn[1] ^ crcIn[2] ^ crcIn[6] ^ crcIn[22] ^ data[1] ^ data[2] ^ data[6];
    assign crcOut[15] = crcIn[2] ^ crcIn[3] ^ crcIn[7] ^ crcIn[23] ^ data[2] ^ data[3] ^ data[7];
    assign crcOut[16] = crcIn[0] ^ crcIn[2] ^ crcIn[3] ^ crcIn[4] ^ crcIn[24] ^ data[0] ^ data[2] ^ data[3] ^ data[4];
    assign crcOut[17] = crcIn[0] ^ crcIn[1] ^ crcIn[3] ^ crcIn[4] ^ crcIn[5] ^ crcIn[25] ^ data[0] ^ data[1] ^ data[3] ^ data[4] ^ data[5];
    assign crcOut[18] = crcIn[0] ^ crcIn[1] ^ crcIn[2] ^ crcIn[4] ^ crcIn[5] ^ crcIn[6] ^ crcIn[26] ^ data[0] ^ data[1] ^ data[2] ^ data[4] ^ data[5] ^ data[6];
    assign crcOut[19] = crcIn[1] ^ crcIn[2] ^ crcIn[3] ^ crcIn[5] ^ crcIn[6] ^ crcIn[7] ^ crcIn[27] ^ data[1] ^ data[2] ^ data[3] ^ data[5] ^ data[6] ^ data[7];
    assign crcOut[20] = crcIn[3] ^ crcIn[4] ^ crcIn[6] ^ crcIn[7] ^ crcIn[28] ^ data[3] ^ data[4] ^ data[6] ^ data[7];
    assign crcOut[21] = crcIn[2] ^ crcIn[4] ^ crcIn[5] ^ crcIn[7] ^ crcIn[29] ^ data[2] ^ data[4] ^ data[5] ^ data[7];
    assign crcOut[22] = crcIn[2] ^ crcIn[3] ^ crcIn[5] ^ crcIn[6] ^ crcIn[30] ^ data[2] ^ data[3] ^ data[5] ^ data[6];
    assign crcOut[23] = crcIn[3] ^ crcIn[4] ^ crcIn[6] ^ crcIn[7] ^ crcIn[31] ^ data[3] ^ data[4] ^ data[6] ^ data[7];
    assign crcOut[24] = crcIn[0] ^ crcIn[2] ^ crcIn[4] ^ crcIn[5] ^ crcIn[7] ^ data[0] ^ data[2] ^ data[4] ^ data[5] ^ data[7];
    assign crcOut[25] = crcIn[0] ^ crcIn[1] ^ crcIn[2] ^ crcIn[3] ^ crcIn[5] ^ crcIn[6] ^ data[0] ^ data[1] ^ data[2] ^ data[3] ^ data[5] ^ data[6];
    assign crcOut[26] = crcIn[0] ^ crcIn[1] ^ crcIn[2] ^ crcIn[3] ^ crcIn[4] ^ crcIn[6] ^ crcIn[7] ^ data[0] ^ data[1] ^ data[2] ^ data[3] ^ data[4] ^ data[6] ^ data[7];
    assign crcOut[27] = crcIn[1] ^ crcIn[3] ^ crcIn[4] ^ crcIn[5] ^ crcIn[7] ^ data[1] ^ data[3] ^ data[4] ^ data[5] ^ data[7];
    assign crcOut[28] = crcIn[0] ^ crcIn[4] ^ crcIn[5] ^ crcIn[6] ^ data[0] ^ data[4] ^ data[5] ^ data[6];
    assign crcOut[29] = crcIn[0] ^ crcIn[1] ^ crcIn[5] ^ crcIn[6] ^ crcIn[7] ^ data[0] ^ data[1] ^ data[5] ^ data[6] ^ data[7];
    assign crcOut[30] = crcIn[0] ^ crcIn[1] ^ crcIn[6] ^ crcIn[7] ^ data[0] ^ data[1] ^ data[6] ^ data[7];
    assign crcOut[31] = crcIn[1] ^ crcIn[7] ^ data[1] ^ data[7];

    always @(posedge clk) begin
        if (reset) begin
            crcIn <= 32'hFF_FF_FF_FF;
        end
        else if (!valid_data || done) begin
            crcIn <= crcIn;
        end
        else begin
            crcIn <= crcOut; // crcIn is the old crcOut
        end
    end

endmodule

test_benches/FCS_tb.v
module FCS_tb;

    reg [7:0] data;
    reg clk, reset, valid_data; // tells us if we are ok to keep going or FIFO paused
    reg done; // 9th bit of FIFO is 1
    wire [31:0] rx_crc;

    //for debugging when we display the values:
    reg display;

    FCS u1(
        .data(data),
        .clk(clk),
        .reset(reset),
        .valid_data(valid_data),
        .done(done),
        .rx_crc(rx_crc)
    );

always #4 clk = ~clk;

integer i;
reg [31:0] expected_out; // for golden vector operations
reg [31:0] magic_res_FCS;
wire match;

assign match = expected_out == rx_crc;
initial begin

    // couldn't figure it out so I added this to visualise it:
    $dumpfile("FCS_tb.vcd");
    $dumpvars(0, FCS_tb);
    //end of added block

    clk = 0;
    reset = 0;
    valid_data = 1;
    done = 0;
    display = 0;

    // empty data (data = h'00):
    data = 8'h00;
    repeat (2) begin
        @(negedge clk)begin
            reset = ~reset; // reset pulse
            #1;
        end
    end
    $display("data is h'00 and will run for 4 clock cycles:");
    expected_out = 32'h2144DF1C;
    repeat (2) begin // 4 - 2 since it would have to wait for the next one after the initial data = h'00 & display occurs at another negedge;
        @(negedge clk) begin
        end
    end

    @(negedge clk);
    repeat (2) begin
        display = ~display; // display pulse
        #1;
    end
    $display("The expected output is: %h", expected_out);
    $display("The actual output is: %h", rx_crc);
    $display("Are they the same? (1 is yes 0 is no): %b", match);


    // standard ASCII test (123456789)
    $display("data is for the ASCII test (123456789) and will run for 9 clock cycles:");
    data = 32'h31;
    reset = 1;
    @(negedge clk)begin
        reset = 0;
    end

    expected_out = 32'hCBF43926;
    repeat (8) begin // 9 - 1 see previous negedge block and surrounding logic
        @(negedge clk) begin
            data = data + 1;
        end
    end
    #1;
    repeat (2) begin
        display = ~display; // display pulse
        #1;
    end
    $display("The expected output is: %h", expected_out);
    $display("The actual output is: %h", rx_crc);
    $display("Are they the same? (1 is yes 0 is no): %b", match);

    //magic residue test (using the same ASCII inputs as previous test):
    magic_res_FCS = rx_crc;

    @(negedge clk);
    // note that the magic residue expected value is that of Ethernet/reflected standard:
    expected_out = 32'h2144DF1C;
    $display("Now appending crcOut to check for magic residue:");
    data = magic_res_FCS[7:0];
    for (i = 1; i < 4; i = i + 1)begin
        @(negedge clk)begin
            data = magic_res_FCS[8*i +: 8];
        end
    end
    #1;
    repeat (2) begin
        display = ~display; // display pulse
        #1;
    end
    $display("The expected output is: %h", expected_out);
    $display("The actual output is: %h", rx_crc);
    $display("Are they the same? (1 is yes 0 is no): %b", match);

    $finish;
end
endmodule

FCS_tb.vcd
$date
	Mon Apr 06 13:06:04 2026
$end
$version
	Icarus Verilog
$end
$timescale
	1s
$end
$scope module FCS_tb $end
$var wire 32 ! rx_crc [31:0] $end
$var wire 1 " match $end
$var reg 1 # clk $end
$var reg 8 $ data [7:0] $end
$var reg 1 % display $end
$var reg 1 & done $end
$var reg 32 ' expected_out [31:0] $end
$var reg 32 ( magic_res_FCS [31:0] $end
$var reg 1 ) reset $end
$var reg 1 * valid_data $end
$var integer 32 + i [31:0] $end
$scope module u1 $end
$var wire 1 # clk $end
$var wire 8 , data [7:0] $end
$var wire 1 & done $end
$var wire 1 ) reset $end
$var wire 32 - rx_crc [31:0] $end
$var wire 1 * valid_data $end
$var wire 32 . crcOut [31:0] $end
$var reg 32 / crcIn [31:0] $end
$upscope $end
$upscope $end
$enddefinitions $end
$comment Show the parameter values. $end
$dumpall
$end
#0
$dumpvars
bx /
bx .
bx -
b0 ,
bx +
1*
0)
bx (
bx '
0&
0%
b0 $
0#
x"
bx !
$end
#4
1#
#8
1)
0#
#12
b11010010000000101110111110001101 !
b11010010000000101110111110001101 -
b101101111111010001000001110010 .
b11111111111111111111111111111111 /
1#
#16
0)
0#
#17
0"
b100001010001001101111100011100 '
#20
b1000001110110010001001011111111 !
b1000001110110010001001011111111 -
b10111110001001101110110100000000 .
b101101111111010001000001110010 /
1#
#24
0#
#28
b11111111010000011101100100010010 !
b11111111010000011101100100010010 -
b101111100010011011101101 .
b10111110001001101110110100000000 /
1#
#32
0#
#36
1"
b100001010001001101111100011100 !
b100001010001001101111100011100 -
b11011110101110110010000011100011 .
b101111100010011011101101 /
1#
#40
1%
0#
#41
0%
#42
0"
b1110000100110101101111100100110 !
b1110000100110101101111100100110 -
b10001111011001010010000011011001 .
1)
b110001 $
b110001 ,
#44
b10000011110111001110111110110111 !
b10000011110111001110111110110111 -
b1111100001000110001000001001000 .
b11111111111111111111111111111111 /
1#
#48
b11001011111101000011100100100110 '
0)
0#
#52
b11010110010110100001010101110111 !
b11010110010110100001010101110111 -
b101001101001011110101010001000 .
b1111100001000110001000001001000 /
1#
#56
b1001111010100110100010011001101 !
b1001111010100110100010011001101 -
b10110000101011001011101100110010 .
b110010 $
b110010 ,
0#
#60
b11111111010011110101001101000100 !
b11111111010011110101001101000100 -
b101100001010110010111011 .
b10110000101011001011101100110010 /
1#
#64
b10001000010010000110001111010010 !
b10001000010010000110001111010010 -
b1110111101101111001110000101101 .
b110011 $
b110011 ,
0#
#68
b101100001110111010100000000 !
b101100001110111010100000000 -
b11111010011110001000101011111111 .
b1110111101101111001110000101101 /
1#
#72
b10011011111000111110000010100011 !
b10011011111000111110000010100011 -
b1100100000111000001111101011100 .
b110100 $
b110100 ,
0#
#76
b10111100111100100000101010001010 !
b10111100111100100000101010001010 -
b1000011000011011111010101110101 .
b1100100000111000001111101011100 /
1#
#80
b11001011111101010011101000011100 !
b11001011111101010011101000011100 -
b110100000010101100010111100011 .
b110101 $
b110101 ,
0#
#84
b10010000011110111000001011011011 !
b10010000011110111000001011011011 -
b1101111100001000111110100100100 .
b110100000010101100010111100011 /
1#
#88
b1001011100101101001101100001 !
b1001011100101101001101100001 -
b11110110100011010010110010011110 .
b110110 $
b110110 ,
0#
#92
b100111000001000101100100001001 !
b100111000001000101100100001001 -
b11011000111110111010011011110110 .
b11110110100011010010110010011110 /
1#
#96
b1010000000000110110100110011111 !
b1010000000000110110100110011111 -
b10101111111111001001011001100000 .
b110111 $
b110111 ,
0#
#100
b1010010111111100011100111110 !
b1010010111111100011100111110 -
b11110101101000000011100011000001 .
b10101111111111001001011001100000 /
1#
#104
b10011010111000001101101010101111 !
b10011010111000001101101010101111 -
b1100101000111110010010101010000 .
b111000 $
b111000 ,
0#
#108
b10111100111100110000100110110000 !
b10111100111100110000100110110000 -
b1000011000011001111011001001111 .
b1100101000111110010010101010000 /
1#
#112
1"
b11001011111101000011100100100110 !
b11001011111101000011100100100110 -
b110100000010111100011011011001 .
b111001 $
b111001 ,
0#
#113
1%
#114
0%
#115
b11001011111101000011100100100110 (
#116
0"
b1011111110000010001011001000001 !
b1011111110000010001011001000001 -
b10100000001111101110100110111110 .
b110100000010111100011011011001 /
1#
#120
b11010010110010010001101110110100 !
b11010010110010010001101110110100 -
b101101001101101110010001001011 .
b1 +
b100110 $
b100110 ,
b100001010001001101111100011100 '
0#
#124
b11001100110100011101010011111110 !
b11001100110100011101010011111110 -
b110011001011100010101100000001 .
b101101001101101110010001001011 /
1#
#128
b1000001110110011101100100001011 !
b1000001110110011101100100001011 -
b10111110001001100010011011110100 .
b10 +
b111001 $
b111001 ,
0#
#132
b11010100101000110011111010100 !
b11010100101000110011111010100 -
b11100101011010111001100000101011 .
b10111110001001100010011011110100 /
1#
#136
b11111111010000011101100111011001 !
b11111111010000011101100111011001 -
b101111100010011000100110 .
b11 +
b11110100 $
b11110100 ,
0#
#140
b10010111001000101111001000100001 !
b10010111001000101111001000100001 -
b1101000110111010000110111011110 .
b101111100010011000100110 /
1#
#144
1"
b100001010001001101111100011100 !
b100001010001001101111100011100 -
b11011110101110110010000011100011 .
b100 +
b11001011 $
b11001011 ,
0#
#145
1%
#146
0%
