Individual_gate_level/TX_MAC.v
`default_nettype none

module TX_MAC(
    input wire clk, 
    input wire reset,
    
    // CHANGED: Replaces rx_control_signal. This tells the MAC that the Arbiter has locked a route.
    input wire tx_active,       
    
    input wire [31:0] FCS_data, // Inherited from your original design
    input wire [7:0] rx_data,   // Sliced 8-bit payload coming directly from the Arbiter
    
    output reg [7:0] tx_data,   
    
    // NEW: Standard GMII/RGMII enable signal. The PHY needs this to know when data on the wire is valid.
    output reg tx_en,           
    
    // NEW: Tells the parallel FCS module exactly when to hash the data, ignoring the preamble/SFD.
    output wire payload_active  
);

    wire [7:0] preamble = 8'h55; 
    wire [7:0] SFD = 8'hD5;      

    // CHANGED: Added IPG_WAIT as a distinct state at the end of the transmission cycle.
    // This provides a safer enforcement of the 12-cycle gap than holding it in IDLE.
    localparam IDLE = 0, PREAMBLE_PUSH = 1, SFD_PUSH = 2, DATA_PUSH = 3, FCS_PUSH = 4, IPG_WAIT = 5;
    
    reg [2:0] state, next_state;
    reg [3:0] counter_IPG; 
    reg [2:0] counter_preamble; 
    reg [1:0] counter_FCS; 

    // The FCS module should only calculate CRC when actual payload bytes are flowing.
    assign payload_active = (state == DATA_PUSH);

    // --- State Transition Logic ---
    always @(*) begin
        case (state)
            // Wake up instantly when the Arbiter asserts the lock.
            IDLE:          next_state = tx_active ? PREAMBLE_PUSH : IDLE;
            
            PREAMBLE_PUSH: next_state = (counter_preamble == 3'd6) ? SFD_PUSH : PREAMBLE_PUSH;
            
            SFD_PUSH:      next_state = DATA_PUSH;
            
            // CHANGED: The MAC no longer looks for an EOF bit. It stays here and streams
            // until the Arbiter drops the tx_active signal.
            DATA_PUSH:     next_state = tx_active ? DATA_PUSH : FCS_PUSH;
            
            // Push the 4 bytes of CRC.
            FCS_PUSH:      next_state = (counter_FCS == 3) ? IPG_WAIT : FCS_PUSH;
            
            // CHANGED: Enforce the mandatory 96ns (12 clock cycles at 125MHz) gap before accepting a new frame.
            IPG_WAIT:      next_state = (counter_IPG == 11) ? IDLE : IPG_WAIT; // this reduces latency by switching the 96ns gap from IDLE to this state
            
            default:       next_state = IDLE;
        endcase
    end

    // --- Output Logic ---
    always @(*) begin
        // Default to safe, zeroed outputs
        tx_data = 8'h0;
        tx_en = 1'b0;

        case (state) 
            PREAMBLE_PUSH: begin tx_data = preamble; tx_en = 1'b1; end
            SFD_PUSH:      begin tx_data = SFD;      tx_en = 1'b1; end
            
            // Stream the Arbiter's data
            DATA_PUSH:     begin tx_data = rx_data;  tx_en = 1'b1; end
            
            // Splice the 32-bit CRC into four 8-bit bytes.
            FCS_PUSH:      begin 
                tx_data = FCS_data[(31 - 8*counter_FCS) -: 8]; 
                tx_en = 1'b1; 
            end
            
            // During IDLE and IPG_WAIT, tx_en drops to 0 so the PHY ignores the zeroes.
            default:       begin tx_data = 8'h0;     tx_en = 1'b0; end 
        endcase
    end

    // --- Sequential Logic & Counters ---
    always @(posedge clk) begin
        if (reset) begin
            state <= IDLE;
            counter_IPG <= 4'h0;
            counter_preamble <= 3'h0;
            counter_FCS <= 2'h0;
        end
        else begin
            state <= next_state;
            
            case (state)
                PREAMBLE_PUSH: counter_preamble <= counter_preamble + 1;
                FCS_PUSH:      counter_FCS <= counter_FCS + 1;
                
                // CHANGED: IPG counter increments here instead of IDLE to ensure a strict gap.
                IPG_WAIT:      counter_IPG <= counter_IPG + 1;
                
                default: begin 
                    // Clear all counters when not in their specific states.
                    counter_IPG <= 4'h0;
                    counter_preamble <= 3'h0;
                    counter_FCS <= 2'h0;
                end
            endcase
        end
    end
endmodule

test_benches/TX_MAC_tb.v
`timescale 1ns/1ps

module TX_MAC_tb;
    reg clk, reset;
    reg tx_active; // Replaces rx_control_signal
    reg [31:0] FCS_data;
    reg [7:0] rx_data;
    
    wire [7:0] tx_data;
    wire tx_en;          // NEW output
    wire payload_active; // NEW output

    TX_MAC u1(
        .clk(clk),
        .reset(reset),
        .tx_active(tx_active),
        .FCS_data(FCS_data),
        .rx_data(rx_data),
        .tx_data(tx_data),
        .tx_en(tx_en),
        .payload_active(payload_active)
    );

    always #4 clk = ~clk; // 125MHz clock

    integer i;

    initial begin
        $dumpfile("TX_MAC_tb.vcd");
        $dumpvars(0, TX_MAC_tb);

        tx_active = 0;
        reset = 1;
        clk = 0;
        FCS_data = 32'hABCDEF12;
        rx_data = 8'h1A;
        
        #8;
        reset = 0;
        
        @(negedge clk);
        // Arbiter grants access
        tx_active = 1;
        
        // Let it run through Preamble (7), SFD (1), and some Data
        for (i = 0; i < 15; i = i + 1) begin
            @(negedge clk) begin
                $display("state: %d, tx_data: %h, tx_en: %b, payload_active: %b", 
                         u1.state, tx_data, tx_en, payload_active);
            end
        end
        
        // Arbiter drops lock (EOF hit)
        @(negedge clk) begin
            tx_active = 0;
            $display("--- tx_active dropped, expecting FCS_PUSH ---");
        end
        
        // Run through FCS (4 cycles) and IPG_WAIT (12 cycles)
        for (i = 0; i < 20; i = i + 1) begin
            @(negedge clk) begin
                $display("state: %d, tx_data: %h, tx_en: %b, IPG_count: %d", 
                         u1.state, tx_data, tx_en, u1.counter_IPG);
            end
        end

        $finish;
    end
endmodule

TX_MAC_tb.vcd
$date
	Wed Aug 05 15:47:41 2026
$end
$version
	Icarus Verilog
$end
$timescale
	1ps
$end
$scope module TX_MAC_tb $end
$var wire 1 ! tx_en $end
$var wire 8 " tx_data [7:0] $end
$var wire 1 # payload_active $end
$var reg 32 $ FCS_data [31:0] $end
$var reg 1 % clk $end
$var reg 1 & reset $end
$var reg 8 ' rx_data [7:0] $end
$var reg 1 ( tx_active $end
$var integer 32 ) i [31:0] $end
$scope module u1 $end
$var wire 32 * FCS_data [31:0] $end
$var wire 8 + SFD [7:0] $end
$var wire 1 % clk $end
$var wire 8 , preamble [7:0] $end
$var wire 1 & reset $end
$var wire 8 - rx_data [7:0] $end
$var wire 1 ( tx_active $end
$var wire 1 # payload_active $end
$var parameter 32 . DATA_PUSH $end
$var parameter 32 / FCS_PUSH $end
$var parameter 32 0 IDLE $end
$var parameter 32 1 IPG_WAIT $end
$var parameter 32 2 PREAMBLE_PUSH $end
$var parameter 32 3 SFD_PUSH $end
$var reg 2 4 counter_FCS [1:0] $end
$var reg 4 5 counter_IPG [3:0] $end
$var reg 3 6 counter_preamble [2:0] $end
$var reg 3 7 next_state [2:0] $end
$var reg 3 8 state [2:0] $end
$var reg 8 9 tx_data [7:0] $end
$var reg 1 ! tx_en $end
$upscope $end
$upscope $end
$enddefinitions $end
$comment Show the parameter values. $end
$dumpall
b10 3
b1 2
b101 1
b0 0
b100 /
b11 .
$end
#0
$dumpvars
b0 9
bx 8
b0 7
bx 6
bx 5
bx 4
b11010 -
b1010101 ,
b11010101 +
b10101011110011011110111100010010 *
bx )
0(
b11010 '
1&
0%
b10101011110011011110111100010010 $
x#
b0 "
0!
$end
#4000
b0 4
b0 6
b0 5
0#
b0 8
1%
#8000
b1 7
b0 )
1(
0%
0&
#12000
1!
b1010101 "
b1010101 9
b1 8
1%
#16000
b1 )
0%
#20000
b1 6
1%
#24000
b10 )
0%
#28000
b10 6
1%
#32000
b11 )
0%
#36000
b11 6
1%
#40000
b100 )
0%
#44000
b100 6
1%
#48000
b101 )
0%
#52000
b101 6
1%
#56000
b110 )
0%
#60000
b10 7
b110 6
1%
#64000
b111 )
0%
#68000
1!
b11010101 "
b11010101 9
b11 7
b111 6
b10 8
1%
#72000
b1000 )
0%
#76000
1!
b11010 "
b11010 9
b0 6
1#
b11 8
1%
#80000
b1001 )
0%
#84000
1%
#88000
b1010 )
0%
#92000
1%
#96000
b1011 )
0%
#100000
1%
#104000
b1100 )
0%
#108000
1%
#112000
b1101 )
0%
#116000
1%
#120000
b1110 )
0%
#124000
1%
#128000
b1111 )
0%
#132000
1%
#136000
b100 7
b0 )
0(
0%
#140000
1!
b10101011 "
b10101011 9
0#
b100 8
1%
#144000
b1 )
0%
#148000
1!
b11001101 "
b11001101 9
b1 4
1%
#152000
b10 )
0%
#156000
1!
b11101111 "
b11101111 9
b10 4
1%
#160000
b11 )
0%
#164000
1!
b10010 "
b10010 9
b101 7
b11 4
1%
#168000
b100 )
0%
#172000
0!
b0 "
b0 9
b0 4
b101 8
1%
#176000
b101 )
0%
#180000
b1 5
1%
#184000
b110 )
0%
#188000
b10 5
1%
#192000
b111 )
0%
#196000
b11 5
1%
#200000
b1000 )
0%
#204000
b100 5
1%
#208000
b1001 )
0%
#212000
b101 5
1%
#216000
b1010 )
0%
#220000
b110 5
1%
#224000
b1011 )
0%
#228000
b111 5
1%
#232000
b1100 )
0%
#236000
b1000 5
1%
#240000
b1101 )
0%
#244000
b1001 5
1%
#248000
b1110 )
0%
#252000
b1010 5
1%
#256000
b1111 )
0%
#260000
b0 7
b1011 5
1%
#264000
b10000 )
0%
#268000
b1100 5
b0 8
1%
#272000
b10001 )
0%
#276000
b0 5
1%
#280000
b10010 )
0%
#284000
1%
#288000
b10011 )
0%
#292000
1%
#296000
b10100 )
0%
